tasker/__init__.py
tasker/attached_stream.py
tasker/instance.py
tasker/manager.py
tasker/task.py
tskmanager-1.0.1.dist-info/METADATA
tskmanager-1.0.1.dist-info/WHEEL
tskmanager-1.0.1.dist-info/top_level.txt
tskmanager-1.0.1.dist-info/RECORD
