Metadata-Version: 2.1
Name: tskmanager
Version: 1.0.1
Summary: Task manager for python
Author-email: Highghlow <highghlow@proton.me>
Project-URL: Homepage, https://github.com/highghlow/tasker
Project-URL: Bug Tracker, https://github.com/highghlow/tasker/issues
Classifier: Programming Language :: Python :: 3
Classifier: License :: OSI Approved :: MIT License
Classifier: Operating System :: OS Independent
Requires-Python: >=3.7
